ImageUI/Colors.py
ImageUI/Defaults.py
ImageUI/Elements.py
ImageUI/Errors.py
ImageUI/ImageUI.py
ImageUI/Settings.py
ImageUI/States.py
ImageUI/Text.py
ImageUI/Translations.py
ImageUI/Variables.py
ImageUI/__init__.py
imageui-0.43.dist-info/licenses/LICENSE
imageui-0.43.dist-info/METADATA
imageui-0.43.dist-info/WHEEL
imageui-0.43.dist-info/top_level.txt
imageui-0.43.dist-info/RECORD
