Metadata-Version: 2.4
Name: ImageUI
Version: 0.43
Summary: A package for easily creating UIs in Python, mainly using OpenCV's drawing functions.
Author: OleFranz
License:                     GNU GENERAL PUBLIC LICENSE
Requires-Python: >=3.9
License-File: LICENSE
Requires-Dist: mouse
Requires-Dist: numpy
Requires-Dist: pillow
Requires-Dist: pynput==1.7.7
Requires-Dist: pywin32
Requires-Dist: keyboard
Requires-Dist: opencv-python
Requires-Dist: deep-translator
Dynamic: license-file
Dynamic: requires-python
